redisshelve/__init__.py
redis_shelve-1.0.3.dist-info/LICENSE
redis_shelve-1.0.3.dist-info/METADATA
redis_shelve-1.0.3.dist-info/WHEEL
redis_shelve-1.0.3.dist-info/top_level.txt
redis_shelve-1.0.3.dist-info/RECORD
