Metadata-Version: 2.1
Name: redis-shelve
Version: 1.0.3
Summary: UNKNOWN
Home-page: https://github.com/FugaCloud/redis-shelve
Author: Niels van Huijstee
Author-email: niels@fuga.cloud
License: GNU Lesser General Public License v3 (LGPLv3)
Platform: UNKNOWN
Requires-Dist: redis
